jestipy/__init__.py
jestipy/async_support.py
jestipy/cli.py
jestipy/core.py
jestipy/lifecycle.py
jestipy/parameterized.py
jestipy-0.1.0.dist-info/METADATA
jestipy-0.1.0.dist-info/WHEEL
jestipy-0.1.0.dist-info/entry_points.txt
jestipy-0.1.0.dist-info/top_level.txt
jestipy-0.1.0.dist-info/RECORD
