Metadata-Version: 2.1
Name: jestipy
Version: 0.1.0
Summary: A Jest-like testing framework for Python
Home-page: https://github.com/GaoFan98/jestipy
Author: Vagif Aghayev
Author-email: vagifaghayev270298@gmail.com
Classifier: Programming Language :: Python :: 3
Classifier: License :: OSI Approved :: MIT License
Classifier: Operating System :: OS Independent
Requires-Python: >=3.6
